transcriptioner/__init__.py
transcriptioner/example.py
transcriptioner/frontend/dist/TEST1.mp3
transcriptioner/frontend/dist/TEST1.txt
transcriptioner/frontend/dist/index.html
transcriptioner/frontend/dist/assets/index-BJ2TQ59N.js
transcriptioner/frontend/dist/assets/index-Gkvn1pe6.css
transcriptioner-0.0.2.dist-info/LICENSE
transcriptioner-0.0.2.dist-info/METADATA
transcriptioner-0.0.2.dist-info/WHEEL
transcriptioner-0.0.2.dist-info/top_level.txt
transcriptioner-0.0.2.dist-info/RECORD
