Metadata-Version: 2.1
Name: transcriptioner
Version: 0.0.2
Summary: Streamlit component for transcribing audio.
Home-page: 
Author: Leon Zong
Author-email: leon@leonzong.com
Requires-Python: >=3.7
License-File: LICENSE
Requires-Dist: streamlit >=0.63
Provides-Extra: devel
Requires-Dist: wheel ; extra == 'devel'
